aiortnetlink/__init__.py
aiortnetlink/__main__.py
aiortnetlink/address.py
aiortnetlink/cli.py
aiortnetlink/client.py
aiortnetlink/gennl.py
aiortnetlink/lazy.py
aiortnetlink/link.py
aiortnetlink/netlink.py
aiortnetlink/netns.py
aiortnetlink/notification.py
aiortnetlink/route.py
aiortnetlink/rtfile.py
aiortnetlink/rule.py
aiortnetlink/tuntap.py
aiortnetlink/constants/arphrdtype.py
aiortnetlink/constants/ctrlattr.py
aiortnetlink/constants/ctrlcmd.py
aiortnetlink/constants/fratype.py
aiortnetlink/constants/icmpv6routerpref.py
aiortnetlink/constants/ifaflag.py
aiortnetlink/constants/ifatype.py
aiortnetlink/constants/ifflag.py
aiortnetlink/constants/iflatype.py
aiortnetlink/constants/iflinkmode.py
aiortnetlink/constants/ifoper.py
aiortnetlink/constants/miscconstants.py
aiortnetlink/constants/nlfamily.py
aiortnetlink/constants/nlflag.py
aiortnetlink/constants/nlmsgtype.py
aiortnetlink/constants/rtatype.py
aiortnetlink/constants/rtcflag.py
aiortnetlink/constants/rtmflag.py
aiortnetlink/constants/rtmtype.py
aiortnetlink/constants/rtnlfamily.py
aiortnetlink/constants/rtnlgroup.py
aiortnetlink/constants/rtntype.py
aiortnetlink/constants/rtprot.py
aiortnetlink/constants/rtscope.py
aiortnetlink/constants/rttable.py
aiortnetlink/constants/tuniffflag.py
aiortnetlink/constants/tunioctl.py
aiortnetlink/structs/ifa_cacheinfo.py
aiortnetlink-0.2.3.dist-info/METADATA
aiortnetlink-0.2.3.dist-info/WHEEL
aiortnetlink-0.2.3.dist-info/entry_points.txt
aiortnetlink-0.2.3.dist-info/licenses/LICENSE
aiortnetlink-0.2.3.dist-info/RECORD
