Metadata-Version: 2.4
Name: aiortnetlink
Version: 0.2.3
Summary: Netlink client for asyncio
Project-URL: source, https://github.com/thomascellerier/aiortnetlink
Author: Thomas Cellerier
Maintainer: Thomas Cellerier
License-File: LICENSE
Requires-Python: >=3.12
